LICENSE.txt
README.md
setup.cfg
setup.py
Laevitas/SDK.py
Laevitas/__init__.py
Laevitas/consts.py
Laevitas/dataclasses.py
Laevitas/test_SDK.py
SDK_Laevitas.egg-info/PKG-INFO
SDK_Laevitas.egg-info/SOURCES.txt
SDK_Laevitas.egg-info/dependency_links.txt
SDK_Laevitas.egg-info/requires.txt
SDK_Laevitas.egg-info/top_level.txt