Metadata-Version: 2.1
Name: SDK-Laevitas
Version: 2.0.0b0
Summary: SDK
Home-page: https://github.com/Elyesbdakhlia
Download-URL: https://github.com/Elyesbdakhlia/API-SDK/archive/refs/tags/v2.0.0-beta.tar.gz
Author: Elyes
Author-email: elyes@laevitas.ch
License: apache-2.0
License-File: LICENSE.txt
